gtracks/__init__.py
gtracks/gff3_to_bed12.py
gtracks/gff3_to_bed6.py
gtracks/gtracks.py
gtracks/hg19.bed12.bed.gz
gtracks/hg38.bed12.bed.gz
gtracks/pancreatic_islet_atac_seq_ins_igf2.bw
gtracks/sp9512.a02u1.bed12.bed.gz
gtracks/sp9512_frond_example.bw
gtracks/sp9512_frond_turion_dmr.bed
gtracks/sp9512_turion_example.bw
gtracks/version.py
gtracks-1.12.6.dist-info/LICENSE
gtracks-1.12.6.dist-info/METADATA
gtracks-1.12.6.dist-info/WHEEL
gtracks-1.12.6.dist-info/entry_points.txt
gtracks-1.12.6.dist-info/top_level.txt
gtracks-1.12.6.dist-info/RECORD
