Metadata-Version: 2.1
Name: gtracks
Version: 1.12.6
Summary: Plot genome track data
Author-email: Anthony Aylward <aaylward@salk.edu>
Project-URL: Homepage, https://gitlab.com/salk-tm/gtracks
Project-URL: Documentation, https://salk-tm.gitlab.io/gtracks
Classifier: Programming Language :: Python :: 3
Classifier: Operating System :: OS Independent
Classifier: License :: OSI Approved :: MIT License
Requires-Python: >=3.7
License-File: LICENSE
Requires-Dist: deeptools
Requires-Dist: pyGenomeTracks
Requires-Dist: seaborn
Requires-Dist: pybedtools
Requires-Dist: gff2bed
